Metadata-Version: 1.2
Name: django-yaaac
Version: 4.1.0
Summary: Django application providing Ajax search capabilities.
Home-page: https://github.com/Starou/django-yaaac
Author: Stanislas Guerra
Author-email: stanislas.guerra@gmail.com
License: BSD Licence
Project-URL: Source Code, https://github.com/Starou/django-yaaac
Project-URL: Issue Tracker, https://github.com/Starou/django-yaaac/issues
Platform: UNKNOWN
Classifier: Environment :: Web Environment
Classifier: Framework :: Django
Classifier: Intended Audience :: Developers
Classifier: License :: OSI Approved :: BSD License
Classifier: Operating System :: OS Independent
Classifier: Programming Language :: Python
Classifier: Programming Language :: Python :: 3
Classifier: Programming Language :: Python :: 3.9
Classifier: Topic :: Internet :: WWW/HTTP
Classifier: Topic :: Internet :: WWW/HTTP :: Dynamic Content
